setup.py
OI_distributions/Binomialdistribution.py
OI_distributions/Gaussiandistribution.py
OI_distributions/Generaldistribution.py
OI_distributions/__init__.py
OI_distributions.egg-info/PKG-INFO
OI_distributions.egg-info/SOURCES.txt
OI_distributions.egg-info/dependency_links.txt
OI_distributions.egg-info/not-zip-safe
OI_distributions.egg-info/top_level.txt