Metadata-Version: 1.0
Name: OI-distributions
Version: 0.1
Summary: Gaussian distributions
Home-page: UNKNOWN
Author: Odeajo Israel
Author-email: UNKNOWN
License: UNKNOWN
Platform: UNKNOWN
